simpadlib/__init__.py
simpadlib/simpad.py
simpadlib-2.2.1.dist-info/LICENSE
simpadlib-2.2.1.dist-info/METADATA
simpadlib-2.2.1.dist-info/WHEEL
simpadlib-2.2.1.dist-info/top_level.txt
simpadlib-2.2.1.dist-info/RECORD
