Metadata-Version: 2.1
Name: simpadlib
Version: 2.2.1
Summary: A library that allows users to interface with their SimPad devices in real-time
Home-page: https://github.com/malevtuber/simpadlib
Author: Ashe Muller
Author-email: contact.notashe@gmail.com
License: UNKNOWN
Project-URL: Bug Reports, https://github.com/malevtuber/simpadlib/issues
Platform: UNKNOWN
Requires-Python: >=3.10
License-File: LICENSE
Requires-Dist: pywinusb (>=0.4.2)
